fluiddata/__init__.py
fluiddata/fluiddata.py
fluiddata-1.0.1.dist-info/DESCRIPTION.rst
fluiddata-1.0.1.dist-info/METADATA
fluiddata-1.0.1.dist-info/RECORD
fluiddata-1.0.1.dist-info/WHEEL
fluiddata-1.0.1.dist-info/metadata.json
fluiddata-1.0.1.dist-info/top_level.txt
