Metadata-Version: 2.0
Name: fluiddata
Version: 1.0.1
Summary: Python API for FluidDATA
Home-page: UNKNOWN
Author: BitPlatter
Author-email: support@bitplatter.com
License: MIT
Project-URL: Documentation, https://docs.bitplatter.com/fluiddata-python/
Keywords: bitplatter fluiddata development
Platform: UNKNOWN
Classifier: Development Status :: 5 - Production/Stable
Classifier: Intended Audience :: Developers
Classifier: Topic :: Software Development :: Libraries :: Python Modules
Classifier: License :: OSI Approved :: MIT License
Classifier: Programming Language :: Python :: 2
Classifier: Programming Language :: Python :: 2.6
Classifier: Programming Language :: Python :: 2.7
Classifier: Programming Language :: Python :: 3
Classifier: Programming Language :: Python :: 3.2
Classifier: Programming Language :: Python :: 3.3
Classifier: Programming Language :: Python :: 3.4
Requires-Dist: requests
